nndm_library/__init__.py
nndm_library/utils/__init__.py
nndm_library/utils/reading_utils.py
nndm_library/utils/utils.py
nndm_library-0.0.26.dist-info/LICENSE
nndm_library-0.0.26.dist-info/METADATA
nndm_library-0.0.26.dist-info/WHEEL
nndm_library-0.0.26.dist-info/top_level.txt
nndm_library-0.0.26.dist-info/RECORD
