Metadata-Version: 2.1
Name: nndm-library
Version: 0.0.26
Summary: Library to read particle files and apply machine learning to them
Home-page: https://nndm-library.readthedocs.io/
Author: Andrés Felipe Gómez, Jose Miguel Muñoz Arias, Esteban Vásquez, Amalia Betancur, Guillermo Palacio
Author-email: andres.gomez27@udea.edu.co
License: MIT
Platform: UNKNOWN
Requires-Python: >=3.8
License-File: LICENSE
Requires-Dist: numpy (>=1.22.0)
Requires-Dist: pandas (>=1.4.1)
Requires-Dist: uproot (>=4.2.0)
Requires-Dist: tqdm (>=4.56.0)
Requires-Dist: pylhe (>=0.2.1)
Requires-Dist: lz4 (>=4.0.0)
Requires-Dist: xxhash (>=3.0.0)
